{
    "emergencies": [
        {
            "id": 1,
            "time": "2015-12-10-17-10-52",
            "location": {
                "lat": 40.2978759,
                "lng": -75.5812935
            },
            "urgencyLevel": 3,
            "suspectedDiagnosis": "BACK PAINS/INJURY",
            "preferredHospital": null
        },
        {
            "id": 2,
            "time": "2015-12-10-17-29-21",
            "location": {
                "lat": 40.2580614,
                "lng": -75.2646799
            },
            "urgencyLevel": 4,
            "suspectedDiagnosis": "DIABETIC EMERGENCY",
            "preferredHospital": null
        },
        {
            "id": 3,
            "time": "2015-12-10-14-39-21",
            "location": {
                "lat": 40.1211818,
                "lng": -75.3519752
            },
            "urgencyLevel": 2,
            "suspectedDiagnosis": "GAS-ODOR/LEAK",
            "preferredHospital": null
        },
        {
            "id": 4,
            "time": "2015-12-10-16-47-36",
            "location": {
                "lat": 40.116153,
                "lng": -75.343513
            },
            "urgencyLevel": 4,
            "suspectedDiagnosis": "CARDIAC EMERGENCY",
            "preferredHospital": null
        },
        {
            "id": 5,
            "time": "2015-12-10-16-56-52",
            "location": {
                "lat": 40.251492,
                "lng": -75.6033497
            },
            "urgencyLevel": 1,
            "suspectedDiagnosis": "DIZZINESS",
            "preferredHospital": null
        },
        {
            "id": 6,
            "time": "2015-12-10-15-39-04",
            "location": {
                "lat": 40.2534732,
                "lng": -75.283245
            },
            "urgencyLevel": 4,
            "suspectedDiagnosis": "HEAD INJURY",
            "preferredHospital": null
        },
        {
            "id": 7,
            "time": "2015-12-10-16-46-48",
            "location": {
                "lat": 40.1821111,
                "lng": -75.1277951
            },
            "urgencyLevel": 3,
            "suspectedDiagnosis": "NAUSEA/VOMITING",
            "preferredHospital": null
        },
        {
            "id": 8,
            "time": "2015-12-10-16-17-05",
            "location": {
                "lat": 40.2172859,
                "lng": -75.405182
            },
            "urgencyLevel": 4,
            "suspectedDiagnosis": "RESPIRATORY EMERGENCY",
            "preferredHospital": null
        },
        {
            "id": 9,
            "time": "2015-12-10-16-51-42",
            "location": {
                "lat": 40.2890267,
                "lng": -75.3995896
            },
            "urgencyLevel": 1,
            "suspectedDiagnosis": "SYNCOPAL EPISODE",
            "preferredHospital": null
        },
        {
            "id": 10,
            "time": "2015-12-10-17-35-41",
            "location": {
                "lat": 40.1023985,
                "lng": -75.2914577
            },
            "urgencyLevel": 4,
            "suspectedDiagnosis": "VEHICLE ACCIDENT -",
            "preferredHospital": 5
        },
        {
            "id": 11,
            "time": "2015-12-10-17-33-50",
            "location": {
                "lat": 40.2319898,
                "lng": -75.2518915
            },
            "urgencyLevel": 4,
            "suspectedDiagnosis": "VEHICLE ACCIDENT -",
            "preferredHospital": null
        },
        {
            "id": 12,
            "time": "2015-12-10-16-32-10",
            "location": {
                "lat": 40.0841613,
                "lng": -75.3083857
            },
            "urgencyLevel": 4,
            "suspectedDiagnosis": "VEHICLE ACCIDENT -",
            "preferredHospital": 4
        },
        {
            "id": 13,
            "time": "2015-12-10-17-15-49",
            "location": {
                "lat": 40.1741312,
                "lng": -75.0984907
            },
            "urgencyLevel": 4,
            "suspectedDiagnosis": "VEHICLE ACCIDENT -",
            "preferredHospital": 2
        },
        {
            "id": 14,
            "time": "2015-12-10-17-12-47",
            "location": {
                "lat": 40.062974,
                "lng": -75.135914
            },
            "urgencyLevel": 4,
            "suspectedDiagnosis": "VEHICLE ACCIDENT -",
            "preferredHospital": 5
        },
        {
            "id": 15,
            "time": "2015-12-10-17-09-49",
            "location": {
                "lat": 40.0972222,
                "lng": -75.3761952
            },
            "urgencyLevel": 4,
            "suspectedDiagnosis": "VEHICLE ACCIDENT -",
            "preferredHospital": 1
        },
        {
            "id": 16,
            "time": "2015-12-10-17-31-00",
            "location": {
                "lat": 40.2237777,
                "lng": -75.2353993
            },
            "urgencyLevel": 4,
            "suspectedDiagnosis": "VEHICLE ACCIDENT -",
            "preferredHospital": 5
        },
        {
            "id": 17,
            "time": "2015-12-10-17-42-44",
            "location": {
                "lat": 40.2432578,
                "lng": -75.2865516
            },
            "urgencyLevel": 4,
            "suspectedDiagnosis": "RESPIRATORY EMERGENCY",
            "preferredHospital": null
        },
        {
            "id": 18,
            "time": "2015-12-10-17-41-54",
            "location": {
                "lat": 40.3121807,
                "lng": -75.5742598
            },
            "urgencyLevel": 1,
            "suspectedDiagnosis": "DIZZINESS",
            "preferredHospital": 1
        },
        {
            "id": 19,
            "time": "2015-12-10-17-43-29",
            "location": {
                "lat": 40.114239,
                "lng": -75.338508
            },
            "urgencyLevel": 4,
            "suspectedDiagnosis": "VEHICLE ACCIDENT",
            "preferredHospital": 2
        },
        {
            "id": 20,
            "time": "2015-12-10-17-45-23",
            "location": {
                "lat": 40.2093369,
                "lng": -75.1352655
            },
            "urgencyLevel": 4,
            "suspectedDiagnosis": "DISABLED VEHICLE -",
            "preferredHospital": null
        },
        {
            "id": 21,
            "time": "2015-12-10-17-43-45",
            "location": {
                "lat": 40.114239,
                "lng": -75.338508
            },
            "urgencyLevel": 4,
            "suspectedDiagnosis": "VEHICLE ACCIDENT -",
            "preferredHospital": null
        },
        {
            "id": 22,
            "time": "2015-12-10-17-53-22",
            "location": {
                "lat": 40.1179476,
                "lng": -75.2098476
            },
            "urgencyLevel": 4,
            "suspectedDiagnosis": "DISABLED VEHICLE -",
            "preferredHospital": null
        },
        {
            "id": 23,
            "time": "2015-12-10-17-59-24",
            "location": {
                "lat": 40.1990064,
                "lng": -75.3000584
            },
            "urgencyLevel": 3,
            "suspectedDiagnosis": "APPLIANCE FIRE",
            "preferredHospital": 5
        },
        {
            "id": 24,
            "time": "2015-12-10-18-00-38",
            "location": {
                "lat": 40.1433257,
                "lng": -75.422819
            },
            "urgencyLevel": 4,
            "suspectedDiagnosis": "DISABLED VEHICLE -",
            "preferredHospital": 4
        },
        {
            "id": 25,
            "time": "2015-12-10-17-58-22",
            "location": {
                "lat": 40.1532684,
                "lng": -75.1895576
            },
            "urgencyLevel": 4,
            "suspectedDiagnosis": "VEHICLE ACCIDENT -",
            "preferredHospital": null
        },
        {
            "id": 26,
            "time": "2015-12-10-18-02-02",
            "location": {
                "lat": 40.1330371,
                "lng": -75.4084631
            },
            "urgencyLevel": 2,
            "suspectedDiagnosis": "GENERAL WEAKNESS",
            "preferredHospital": null
        },
        {
            "id": 27,
            "time": "2015-12-10-18-02-38",
            "location": {
                "lat": 40.1552833,
                "lng": -75.2642296
            },
            "urgencyLevel": 4,
            "suspectedDiagnosis": "HEAD INJURY",
            "preferredHospital": 2
        },
        {
            "id": 28,
            "time": "2015-12-10-18-05-19",
            "location": {
                "lat": 40.0289031,
                "lng": -75.3518224
            },
            "urgencyLevel": 1,
            "suspectedDiagnosis": "CARBON MONOXIDE DETECTOR",
            "preferredHospital": null
        },
        {
            "id": 29,
            "time": "2015-12-10-18-05-39",
            "location": {
                "lat": 40.0972222,
                "lng": -75.3761952
            },
            "urgencyLevel": 4,
            "suspectedDiagnosis": "VEHICLE ACCIDENT -",
            "preferredHospital": 1
        },
        {
            "id": 30,
            "time": "2015-12-10-18-10-40",
            "location": {
                "lat": 40.2093369,
                "lng": -75.1352655
            },
            "urgencyLevel": 4,
            "suspectedDiagnosis": "DISABLED VEHICLE -",
            "preferredHospital": null
        },
        {
            "id": 31,
            "time": "2015-12-10-18-07-01",
            "location": {
                "lat": 40.0972222,
                "lng": -75.3761952
            },
            "urgencyLevel": 4,
            "suspectedDiagnosis": "VEHICLE ACCIDENT -",
            "preferredHospital": null
        },
        {
            "id": 32,
            "time": "2015-12-10-18-09-49",
            "location": {
                "lat": 40.300736,
                "lng": -75.3319733
            },
            "urgencyLevel": 4,
            "suspectedDiagnosis": "RESPIRATORY EMERGENCY",
            "preferredHospital": 3
        },
        {
            "id": 33,
            "time": "2015-12-10-18-17-07",
            "location": {
                "lat": 40.129398,
                "lng": -75.3322134
            },
            "urgencyLevel": 3,
            "suspectedDiagnosis": "UNKNOWN MEDICAL EMERGENCY",
            "preferredHospital": 3
        },
        {
            "id": 34,
            "time": "2015-12-10-18-21-43",
            "location": {
                "lat": 40.0993621,
                "lng": -75.1500348
            },
            "urgencyLevel": 4,
            "suspectedDiagnosis": "VEHICLE ACCIDENT -",
            "preferredHospital": null
        },
        {
            "id": 35,
            "time": "2015-12-10-18-23-13",
            "location": {
                "lat": 40.2212266,
                "lng": -75.2887369
            },
            "urgencyLevel": 4,
            "suspectedDiagnosis": "DISABLED VEHICLE -",
            "preferredHospital": 5
        },
        {
            "id": 36,
            "time": "2015-12-10-18-20-28",
            "location": {
                "lat": 40.0738642,
                "lng": -75.3167972
            },
            "urgencyLevel": 4,
            "suspectedDiagnosis": "DISABLED VEHICLE -",
            "preferredHospital": 1
        },
        {
            "id": 37,
            "time": "2015-12-10-18-23-11",
            "location": {
                "lat": 40.1617316,
                "lng": -75.1510554
            },
            "urgencyLevel": 4,
            "suspectedDiagnosis": "VEHICLE ACCIDENT -",
            "preferredHospital": null
        },
        {
            "id": 38,
            "time": "2015-12-10-18-29-54",
            "location": {
                "lat": 40.0667184,
                "lng": -75.307176
            },
            "urgencyLevel": 4,
            "suspectedDiagnosis": "VEHICLE ACCIDENT",
            "preferredHospital": null
        },
        {
            "id": 39,
            "time": "2015-12-10-18-30-41",
            "location": {
                "lat": 40.0655304,
                "lng": -75.3078284
            },
            "urgencyLevel": 4,
            "suspectedDiagnosis": "VEHICLE ACCIDENT -",
            "preferredHospital": 1
        },
        {
            "id": 40,
            "time": "2015-12-10-18-32-25",
            "location": {
                "lat": 40.1042063,
                "lng": -75.3676652
            },
            "urgencyLevel": 2,
            "suspectedDiagnosis": "GAS-ODOR/LEAK",
            "preferredHospital": null
        },
        {
            "id": 41,
            "time": "2015-12-10-18-38-18",
            "location": {
                "lat": 40.1227798,
                "lng": -75.2672413
            },
            "urgencyLevel": 3,
            "suspectedDiagnosis": "UNRESPONSIVE SUBJECT",
            "preferredHospital": null
        },
        {
            "id": 42,
            "time": "2015-12-10-18-37-00",
            "location": {
                "lat": 40.091055,
                "lng": -75.3843648
            },
            "urgencyLevel": 4,
            "suspectedDiagnosis": "VEHICLE ACCIDENT -",
            "preferredHospital": null
        },
        {
            "id": 43,
            "time": "2015-12-10-18-43-07",
            "location": {
                "lat": 40.0249667,
                "lng": -75.2829046
            },
            "urgencyLevel": 4,
            "suspectedDiagnosis": "CARDIAC EMERGENCY",
            "preferredHospital": null
        },
        {
            "id": 44,
            "time": "2015-12-10-18-47-18",
            "location": {
                "lat": 40.1257391,
                "lng": -75.339822
            },
            "urgencyLevel": 4,
            "suspectedDiagnosis": "VEHICLE ACCIDENT -",
            "preferredHospital": null
        },
        {
            "id": 45,
            "time": "2015-12-10-18-50-37",
            "location": {
                "lat": 40.2249227,
                "lng": -75.5280446
            },
            "urgencyLevel": 4,
            "suspectedDiagnosis": "VEHICLE ACCIDENT",
            "preferredHospital": 3
        },
        {
            "id": 46,
            "time": "2015-12-10-18-50-23",
            "location": {
                "lat": 40.2249227,
                "lng": -75.5280446
            },
            "urgencyLevel": 4,
            "suspectedDiagnosis": "VEHICLE ACCIDENT",
            "preferredHospital": null
        },
        {
            "id": 47,
            "time": "2015-12-10-18-51-34",
            "location": {
                "lat": 40.2249227,
                "lng": -75.5280446
            },
            "urgencyLevel": 4,
            "suspectedDiagnosis": "VEHICLE ACCIDENT -",
            "preferredHospital": null
        },
        {
            "id": 48,
            "time": "2015-12-10-18-51-01",
            "location": {
                "lat": 40.2309343,
                "lng": -75.5221245
            },
            "urgencyLevel": 4,
            "suspectedDiagnosis": "VEHICLE ACCIDENT -",
            "preferredHospital": null
        },
        {
            "id": 49,
            "time": "2015-12-10-18-59-50",
            "location": {
                "lat": 40.251523,
                "lng": -75.329557
            },
            "urgencyLevel": 1,
            "suspectedDiagnosis": "ALTERED MENTAL STATUS",
            "preferredHospital": 2
        },
        {
            "id": 50,
            "time": "2015-12-10-18-56-51",
            "location": {
                "lat": 40.1653934,
                "lng": -75.2829046
            },
            "urgencyLevel": 4,
            "suspectedDiagnosis": "FIRE ALARM",
            "preferredHospital": 3
        },
        {
            "id": 51,
            "time": "2015-12-10-19-06-07",
            "location": {
                "lat": 40.2313745,
                "lng": -75.2797803
            },
            "urgencyLevel": 4,
            "suspectedDiagnosis": "VEHICLE ACCIDENT -",
            "preferredHospital": 4
        },
        {
            "id": 52,
            "time": "2015-12-10-19-07-27",
            "location": {
                "lat": 40.3209665,
                "lng": -75.6113493
            },
            "urgencyLevel": 3,
            "suspectedDiagnosis": "CVA/STROKE",
            "preferredHospital": null
        },
        {
            "id": 53,
            "time": "2015-12-10-19-09-42",
            "location": {
                "lat": 40.0512834,
                "lng": -75.2968515
            },
            "urgencyLevel": 4,
            "suspectedDiagnosis": "FIRE ALARM",
            "preferredHospital": null
        },
        {
            "id": 54,
            "time": "2015-12-10-19-08-43",
            "location": {
                "lat": 40.2432612,
                "lng": -75.2960797
            },
            "urgencyLevel": 2,
            "suspectedDiagnosis": "ROAD OBSTRUCTION -",
            "preferredHospital": null
        },
        {
            "id": 55,
            "time": "2015-12-10-19-18-31",
            "location": {
                "lat": 40.1568468,
                "lng": -75.1019942
            },
            "urgencyLevel": 2,
            "suspectedDiagnosis": "UNKNOWN MEDICAL EMERGENCY",
            "preferredHospital": null
        },
        {
            "id": 56,
            "time": "2015-12-10-19-12-13",
            "location": {
                "lat": 40.1330371,
                "lng": -75.4084631
            },
            "urgencyLevel": 2,
            "suspectedDiagnosis": "CVA/STROKE",
            "preferredHospital": null
        },
        {
            "id": 57,
            "time": "2015-12-10-19-15-10",
            "location": {
                "lat": 40.089973,
                "lng": -75.1410849
            },
            "urgencyLevel": 1,
            "suspectedDiagnosis": "SUBJECT IN PAIN",
            "preferredHospital": null
        },
        {
            "id": 58,
            "time": "2015-12-10-19-17-13",
            "location": {
                "lat": 40.2470021,
                "lng": -75.6525972
            },
            "urgencyLevel": 2,
            "suspectedDiagnosis": "SUBJECT IN PAIN",
            "preferredHospital": null
        },
        {
            "id": 59,
            "time": "2015-12-10-19-19-19",
            "location": {
                "lat": 40.0818005,
                "lng": -75.2531616
            },
            "urgencyLevel": 4,
            "suspectedDiagnosis": "DISABLED VEHICLE -",
            "preferredHospital": null
        },
        {
            "id": 60,
            "time": "2015-12-10-19-25-22",
            "location": {
                "lat": 40.0203725,
                "lng": -75.3092584
            },
            "urgencyLevel": 4,
            "suspectedDiagnosis": "DISABLED VEHICLE -",
            "preferredHospital": null
        },
        {
            "id": 61,
            "time": "2015-12-10-19-06-07",
            "location": {
                "lat": 40.2306331,
                "lng": -75.2785377
            },
            "urgencyLevel": 4,
            "suspectedDiagnosis": "VEHICLE ACCIDENT -",
            "preferredHospital": null
        },
        {
            "id": 62,
            "time": "2015-12-10-19-23-08",
            "location": {
                "lat": 40.1173446,
                "lng": -75.2111725
            },
            "urgencyLevel": 2,
            "suspectedDiagnosis": "HEMORRHAGING",
            "preferredHospital": null
        },
        {
            "id": 63,
            "time": "2015-12-10-19-25-07",
            "location": {
                "lat": 40.2679249,
                "lng": -75.3143823
            },
            "urgencyLevel": 1,
            "suspectedDiagnosis": "UNKNOWN MEDICAL EMERGENCY",
            "preferredHospital": null
        },
        {
            "id": 64,
            "time": "2015-12-10-19-22-25",
            "location": {
                "lat": 40.2456734,
                "lng": -75.2796667
            },
            "urgencyLevel": 4,
            "suspectedDiagnosis": "FALL VICTIM",
            "preferredHospital": 5
        },
        {
            "id": 65,
            "time": "2015-12-10-19-21-47",
            "location": {
                "lat": 40.1199455,
                "lng": -75.3383214
            },
            "urgencyLevel": 4,
            "suspectedDiagnosis": "RESPIRATORY EMERGENCY",
            "preferredHospital": null
        },
        {
            "id": 66,
            "time": "2015-12-10-19-35-47",
            "location": {
                "lat": 40.105308,
                "lng": -75.341987
            },
            "urgencyLevel": 1,
            "suspectedDiagnosis": "ASSAULT VICTIM",
            "preferredHospital": 5
        },
        {
            "id": 67,
            "time": "2015-12-10-19-38-31",
            "location": {
                "lat": 40.2890267,
                "lng": -75.3995896
            },
            "urgencyLevel": 4,
            "suspectedDiagnosis": "FALL VICTIM",
            "preferredHospital": null
        },
        {
            "id": 68,
            "time": "2015-12-10-19-43-24",
            "location": {
                "lat": 40.245731,
                "lng": -75.3416869
            },
            "urgencyLevel": 4,
            "suspectedDiagnosis": "RESPIRATORY EMERGENCY",
            "preferredHospital": null
        },
        {
            "id": 69,
            "time": "2015-12-10-19-49-37",
            "location": {
                "lat": 40.1330371,
                "lng": -75.4084631
            },
            "urgencyLevel": 2,
            "suspectedDiagnosis": "SUBJECT IN PAIN",
            "preferredHospital": 4
        },
        {
            "id": 70,
            "time": "2015-12-10-19-54-45",
            "location": {
                "lat": 40.1546593,
                "lng": -75.2215435
            },
            "urgencyLevel": 2,
            "suspectedDiagnosis": "SEIZURES",
            "preferredHospital": 1
        },
        {
            "id": 71,
            "time": "2015-12-10-20-01-29",
            "location": {
                "lat": 40.0249667,
                "lng": -75.2829046
            },
            "urgencyLevel": 3,
            "suspectedDiagnosis": "GAS-ODOR/LEAK",
            "preferredHospital": null
        },
        {
            "id": 72,
            "time": "2015-12-10-20-05-27",
            "location": {
                "lat": 39.9867698,
                "lng": -75.2754335
            },
            "urgencyLevel": 4,
            "suspectedDiagnosis": "DIABETIC EMERGENCY",
            "preferredHospital": null
        },
        {
            "id": 73,
            "time": "2015-12-10-20-10-27",
            "location": {
                "lat": 40.2537881,
                "lng": -75.2164375
            },
            "urgencyLevel": 2,
            "suspectedDiagnosis": "SUBJECT IN PAIN",
            "preferredHospital": null
        },
        {
            "id": 74,
            "time": "2015-12-10-20-09-47",
            "location": {
                "lat": 40.2450058,
                "lng": -75.5930476
            },
            "urgencyLevel": 3,
            "suspectedDiagnosis": "UNKNOWN MEDICAL EMERGENCY",
            "preferredHospital": null
        },
        {
            "id": 75,
            "time": "2015-12-10-20-06-36",
            "location": {
                "lat": 40.295271,
                "lng": -75.3284004
            },
            "urgencyLevel": 4,
            "suspectedDiagnosis": "HEAD INJURY",
            "preferredHospital": null
        },
        {
            "id": 76,
            "time": "2015-12-10-20-07-25",
            "location": {
                "lat": 40.2048367,
                "lng": -75.2228211
            },
            "urgencyLevel": 4,
            "suspectedDiagnosis": "VEHICLE ACCIDENT -",
            "preferredHospital": null
        },
        {
            "id": 77,
            "time": "2015-12-10-20-24-17",
            "location": {
                "lat": 40.2442013,
                "lng": -75.582403
            },
            "urgencyLevel": 4,
            "suspectedDiagnosis": "DISABLED VEHICLE -",
            "preferredHospital": null
        },
        {
            "id": 78,
            "time": "2015-12-10-20-26-35",
            "location": {
                "lat": 40.2315111,
                "lng": -75.6545599
            },
            "urgencyLevel": 4,
            "suspectedDiagnosis": "FALL VICTIM",
            "preferredHospital": 5
        },
        {
            "id": 79,
            "time": "2015-12-10-20-26-14",
            "location": {
                "lat": 40.1142023,
                "lng": -75.3268041
            },
            "urgencyLevel": 4,
            "suspectedDiagnosis": "FALL VICTIM",
            "preferredHospital": 2
        },
        {
            "id": 80,
            "time": "2015-12-10-20-36-49",
            "location": {
                "lat": 40.0039548,
                "lng": -75.2207009
            },
            "urgencyLevel": 4,
            "suspectedDiagnosis": "VEHICLE ACCIDENT -",
            "preferredHospital": 3
        },
        {
            "id": 81,
            "time": "2015-12-10-20-45-14",
            "location": {
                "lat": 40.2906932,
                "lng": -75.5766612
            },
            "urgencyLevel": 1,
            "suspectedDiagnosis": "SYNCOPAL EPISODE",
            "preferredHospital": null
        },
        {
            "id": 82,
            "time": "2015-12-10-20-43-44",
            "location": {
                "lat": 40.0074347,
                "lng": -75.2489886
            },
            "urgencyLevel": 3,
            "suspectedDiagnosis": "CARBON MONOXIDE DETECTOR",
            "preferredHospital": null
        },
        {
            "id": 83,
            "time": "2015-12-10-20-50-14",
            "location": {
                "lat": 40.2304548,
                "lng": -75.6339815
            },
            "urgencyLevel": 3,
            "suspectedDiagnosis": "MEDICAL ALERT ALARM",
            "preferredHospital": null
        },
        {
            "id": 84,
            "time": "2015-12-10-20-49-08",
            "location": {
                "lat": 40.0348666,
                "lng": -75.3276061
            },
            "urgencyLevel": 4,
            "suspectedDiagnosis": "RESPIRATORY EMERGENCY",
            "preferredHospital": null
        },
        {
            "id": 85,
            "time": "2015-12-10-20-53-30",
            "location": {
                "lat": 40.0167386,
                "lng": -75.2651596
            },
            "urgencyLevel": 1,
            "suspectedDiagnosis": "ABDOMINAL PAINS",
            "preferredHospital": 4
        },
        {
            "id": 86,
            "time": "2015-12-10-21-01-26",
            "location": {
                "lat": 40.4142488,
                "lng": -75.5090155
            },
            "urgencyLevel": 4,
            "suspectedDiagnosis": "FIRE ALARM",
            "preferredHospital": 5
        },
        {
            "id": 87,
            "time": "2015-12-10-21-10-36",
            "location": {
                "lat": 40.0809133,
                "lng": -75.2026651
            },
            "urgencyLevel": 4,
            "suspectedDiagnosis": "RESPIRATORY EMERGENCY",
            "preferredHospital": 4
        },
        {
            "id": 88,
            "time": "2015-12-10-21-12-35",
            "location": {
                "lat": 40.2372576,
                "lng": -75.2204062
            },
            "urgencyLevel": 1,
            "suspectedDiagnosis": "UNRESPONSIVE SUBJECT",
            "preferredHospital": 2
        },
        {
            "id": 89,
            "time": "2015-12-10-21-19-21",
            "location": {
                "lat": 40.2500156,
                "lng": -75.5921595
            },
            "urgencyLevel": 2,
            "suspectedDiagnosis": "ROAD OBSTRUCTION -",
            "preferredHospital": 3
        },
        {
            "id": 90,
            "time": "2015-12-10-21-24-47",
            "location": {
                "lat": 40.2469315,
                "lng": -75.6439204
            },
            "urgencyLevel": 1,
            "suspectedDiagnosis": "PUMP DETAIL",
            "preferredHospital": null
        },
        {
            "id": 91,
            "time": "2015-12-10-21-31-19",
            "location": {
                "lat": 40.230284,
                "lng": -75.3540007
            },
            "urgencyLevel": 4,
            "suspectedDiagnosis": "VEHICLE ACCIDENT -",
            "preferredHospital": null
        },
        {
            "id": 92,
            "time": "2015-12-10-21-36-01",
            "location": {
                "lat": 40.085487,
                "lng": -75.0977084
            },
            "urgencyLevel": 2,
            "suspectedDiagnosis": "FIRE INVESTIGATION",
            "preferredHospital": null
        },
        {
            "id": 93,
            "time": "2015-12-10-21-31-19",
            "location": {
                "lat": 40.2344178,
                "lng": -75.3513217
            },
            "urgencyLevel": 4,
            "suspectedDiagnosis": "VEHICLE ACCIDENT -",
            "preferredHospital": null
        },
        {
            "id": 94,
            "time": "2015-12-10-21-47-14",
            "location": {
                "lat": 40.0830785,
                "lng": -75.1011171
            },
            "urgencyLevel": 4,
            "suspectedDiagnosis": "DISABLED VEHICLE -",
            "preferredHospital": null
        },
        {
            "id": 95,
            "time": "2015-12-10-21-56-14",
            "location": {
                "lat": 40.2763043,
                "lng": -75.5650236
            },
            "urgencyLevel": 4,
            "suspectedDiagnosis": "DISABLED VEHICLE -",
            "preferredHospital": null
        },
        {
            "id": 96,
            "time": "2015-12-10-21-58-11",
            "location": {
                "lat": 40.0953195,
                "lng": -75.1934818
            },
            "urgencyLevel": 4,
            "suspectedDiagnosis": "VEHICLE ACCIDENT -",
            "preferredHospital": null
        },
        {
            "id": 97,
            "time": "2015-12-10-22-03-14",
            "location": {
                "lat": 40.1514759,
                "lng": -75.3966243
            },
            "urgencyLevel": 2,
            "suspectedDiagnosis": "CVA/STROKE",
            "preferredHospital": 5
        },
        {
            "id": 98,
            "time": "2015-12-10-22-24-21",
            "location": {
                "lat": 40.127611,
                "lng": -75.3799147
            },
            "urgencyLevel": 4,
            "suspectedDiagnosis": "FALL VICTIM",
            "preferredHospital": 4
        },
        {
            "id": 99,
            "time": "2015-12-10-22-22-38",
            "location": {
                "lat": 40.284455,
                "lng": -75.574528
            },
            "urgencyLevel": 3,
            "suspectedDiagnosis": "SEIZURES",
            "preferredHospital": null
        },
        {
            "id": 100,
            "time": "2015-12-10-22-29-17",
            "location": {
                "lat": 40.1201276,
                "lng": -75.3501929
            },
            "urgencyLevel": 4,
            "suspectedDiagnosis": "CARDIAC EMERGENCY",
            "preferredHospital": 2
        },
        {
            "id": 101,
            "time": "2015-12-10-22-27-24",
            "location": {
                "lat": 40.1508958,
                "lng": -75.1274376
            },
            "urgencyLevel": 3,
            "suspectedDiagnosis": "OVERDOSE",
            "preferredHospital": null
        },
        {
            "id": 102,
            "time": "2015-12-10-22-35-51",
            "location": {
                "lat": 40.1825726,
                "lng": -75.5406694
            },
            "urgencyLevel": 4,
            "suspectedDiagnosis": "FIRE ALARM",
            "preferredHospital": 2
        },
        {
            "id": 103,
            "time": "2015-12-10-22-41-53",
            "location": {
                "lat": 40.060048,
                "lng": -75.097217
            },
            "urgencyLevel": 4,
            "suspectedDiagnosis": "VEHICLE ACCIDENT -",
            "preferredHospital": 1
        },
        {
            "id": 104,
            "time": "2015-12-10-22-54-53",
            "location": {
                "lat": 40.2449124,
                "lng": -75.6443631
            },
            "urgencyLevel": 4,
            "suspectedDiagnosis": "FALL VICTIM",
            "preferredHospital": null
        },
        {
            "id": 105,
            "time": "2015-12-10-22-52-55",
            "location": {
                "lat": 40.1388986,
                "lng": -75.1514572
            },
            "urgencyLevel": 1,
            "suspectedDiagnosis": "GAS-ODOR/LEAK",
            "preferredHospital": null
        },
        {
            "id": 106,
            "time": "2015-12-10-22-55-35",
            "location": {
                "lat": 40.1330371,
                "lng": -75.4084631
            },
            "urgencyLevel": 1,
            "suspectedDiagnosis": "ABDOMINAL PAINS",
            "preferredHospital": null
        },
        {
            "id": 107,
            "time": "2015-12-10-23-01-58",
            "location": {
                "lat": 39.9997391,
                "lng": -75.2557489
            },
            "urgencyLevel": 4,
            "suspectedDiagnosis": "FIRE ALARM",
            "preferredHospital": null
        },
        {
            "id": 108,
            "time": "2015-12-10-23-02-27",
            "location": {
                "lat": 40.0177675,
                "lng": -75.2300543
            },
            "urgencyLevel": 4,
            "suspectedDiagnosis": "DISABLED VEHICLE -",
            "preferredHospital": null
        },
        {
            "id": 109,
            "time": "2015-12-10-23-10-34",
            "location": {
                "lat": 40.2449124,
                "lng": -75.6443631
            },
            "urgencyLevel": 1,
            "suspectedDiagnosis": "SUBJECT IN PAIN",
            "preferredHospital": 2
        },
        {
            "id": 110,
            "time": "2015-12-10-23-06-39",
            "location": {
                "lat": 40.0809133,
                "lng": -75.2026651
            },
            "urgencyLevel": 4,
            "suspectedDiagnosis": "RESPIRATORY EMERGENCY",
            "preferredHospital": null
        },
        {
            "id": 111,
            "time": "2015-12-10-23-16-10",
            "location": {
                "lat": 40.0878981,
                "lng": -75.2629699
            },
            "urgencyLevel": 3,
            "suspectedDiagnosis": "NAUSEA/VOMITING",
            "preferredHospital": 2
        },
        {
            "id": 112,
            "time": "2015-12-10-23-32-46",
            "location": {
                "lat": 40.0975908,
                "lng": -75.2525369
            },
            "urgencyLevel": 2,
            "suspectedDiagnosis": "ABDOMINAL PAINS",
            "preferredHospital": null
        },
        {
            "id": 113,
            "time": "2015-12-10-23-45-50",
            "location": {
                "lat": 40.2451166,
                "lng": -75.6460071
            },
            "urgencyLevel": 4,
            "suspectedDiagnosis": "DISABLED VEHICLE -",
            "preferredHospital": null
        },
        {
            "id": 114,
            "time": "2015-12-10-23-58-13",
            "location": {
                "lat": 40.1550603,
                "lng": -75.1022513
            },
            "urgencyLevel": 4,
            "suspectedDiagnosis": "CARDIAC EMERGENCY",
            "preferredHospital": 4
        }
    ]
}
